{"generatedAt": "2026-07-24T10:08:32Z", "weekStart": "2026-07-24", "events": [{"uid": "74q3ce1j6phjab9mcorj2b9k70pmab9o65h6cbb668om8dr5ccoj6p1k70", "title": "Carter needs soccer gear", "allDay": true, "start": "2026-07-25", "end": "2026-07-25", "source": "corey", "location": ""}, {"uid": "f6gu8von15jmlc2ikp2576ok55_20260725T130000Z", "title": "Work 9-2", "allDay": false, "start": "2026-07-25T09:00:00", "end": "2026-07-25T14:00:00", "source": "tamara", "location": ""}, {"uid": "c5i6cp32c4o3cb9kccsjab9kcdi36bb26ss3gbb36hgj2p1o6gs36p9m60_20260729T220000Z", "title": "Gregg Nemschoff", "allDay": false, "start": "2026-07-29T18:00:00", "end": "2026-07-29T19:00:00", "source": "tamara", "location": ""}]}